cz_conventional_jira/__init__.py
cz_conventional_jira/cz_conventional_jira.py
cz_conventional_jira-0.1.4.dist-info/LICENSE
cz_conventional_jira-0.1.4.dist-info/METADATA
cz_conventional_jira-0.1.4.dist-info/WHEEL
cz_conventional_jira-0.1.4.dist-info/entry_points.txt
cz_conventional_jira-0.1.4.dist-info/RECORD
