Metadata-Version: 2.3
Name: cz-conventional-jira
Version: 0.1.4
Summary: Commitizen ruleset extending Conventional Commits with JIRA issue links
License: MIT
Requires-Python: >=3.12
Classifier: License :: OSI Approved :: MIT License
Classifier: Programming Language :: Python :: 3
Classifier: Programming Language :: Python :: 3.12
Classifier: Programming Language :: Python :: 3.13
Provides-Extra: test
Requires-Dist: commitizen (>=4.8.3)
Requires-Dist: pytest (>=8) ; extra == "test"
